README.md
setup.py
idalink/__init__.py
idalink/client.py
idalink/errors.py
idalink/memory.py
idalink/server.py
idalink.egg-info/PKG-INFO
idalink.egg-info/SOURCES.txt
idalink.egg-info/dependency_links.txt
idalink.egg-info/requires.txt
idalink.egg-info/top_level.txt