Metadata-Version: 1.2
Name: idalink
Version: 0.12
Summary: An interface to the insides of IDA!
Home-page: https://github.com/zardus/idalink
Author: Zardus
Author-email: zardus@gmail.com
Maintainer: rhelmot
Maintainer-email: audrey@rhelmot.io
License: GNU General Public License v3
Platform: UNKNOWN
